disdrop/__init__.py
disdrop/advanced_optimizer.py
disdrop/automated_workflow.py
disdrop/cli.py
disdrop/config_manager.py
disdrop/ffmpeg_utils.py
disdrop/file_validator.py
disdrop/gif_generator.py
disdrop/gif_optimizer_advanced.py
disdrop/hardware_detector.py
disdrop/logger_setup.py
disdrop/performance_enhancer.py
disdrop/video_compressor.py
disdrop/video_segmenter.py
disdrop/config/gif_settings.yaml
disdrop/config/logging.yaml
disdrop/config/video_compression.yaml
disdrop-0.1.2.dist-info/licenses/LICENSE
disdrop-0.1.2.dist-info/METADATA
disdrop-0.1.2.dist-info/WHEEL
disdrop-0.1.2.dist-info/entry_points.txt
disdrop-0.1.2.dist-info/top_level.txt
disdrop-0.1.2.dist-info/RECORD
