Metadata-Version: 2.4
Name: disdrop
Version: 0.1.2
Summary: Compress videos and create platform-optimized GIFs (Discord/Twitter/etc.)
Author: Disdrop
License: MIT License
Keywords: video,gif,compression,ffmpeg,discord,twitter
Classifier: Programming Language :: Python :: 3
Classifier: License :: OSI Approved :: MIT License
Classifier: Operating System :: OS Independent
Classifier: Topic :: Multimedia :: Video
Requires-Python: >=3.10
License-File: LICENSE
Requires-Dist: opencv-python>=4.8.0
Requires-Dist: Pillow>=10.1.0
Requires-Dist: PyYAML>=6.0
Requires-Dist: colorama>=0.4.6
Requires-Dist: tqdm>=4.66.0
Requires-Dist: psutil>=5.9.0
Requires-Dist: numpy>=1.24.0
Requires-Dist: platformdirs>=3.10
Dynamic: license-file
